{
  "3/4 Sit-Up": "3/4 仰卧起坐",
  "90/90 Hamstring": "90/90 腘绳肌拉伸",
  "Ab Crunch Machine": "器械卷腹",
  "Ab Roller": "健腹轮",
  "Adductor": "内收肌",
  "Adductor/Groin": "内收肌/腹股沟",
  "Advanced Kettlebell Windmill": "高级壶铃风车",
  "Air Bike": "空中蹬车",
  "All Fours Quad Stretch": "四肢着地四头肌拉伸",
  "Alternate Hammer Curl": "交替锤式弯举",
  "Alternate Heel Touchers": "交替脚跟触碰",
  "Alternate Incline Dumbbell Curl": "交替上斜哑铃弯举",
  "Alternate Leg Diagonal Bound": "交替腿部对角线跳跃",
  "Alternating Cable Shoulder Press": "交替绳索肩推举",
  "Alternating Deltoid Raise": "交替三角肌举",
  "Alternating Floor Press": "交替地板推举",
  "Alternating Hang Clean": "交替悬挂翻举",
  "Alternating Kettlebell Press": "交替壶铃推举",
  "Alternating Kettlebell Row": "交替壶铃划船",
  "Alternating Renegade Row": "交替叛徒式划船",
  "Ankle Circles": "脚踝画圈",
  "Ankle On The Knee": "四字形拉伸",
  "Anterior Tibialis-SMR": "前侧胫骨前肌筋膜放松",
  "Anti-Gravity Press": "反重力推举",
  "Arm Circles": "臂画圈",
  "Arnold Dumbbell Press": "阿诺德哑铃推举",
  "Around The Worlds": "环绕世界",
  "Atlas Stone Trainer": "阿特拉斯石训练器",
  "Atlas Stones": "阿特拉斯石",
  "Axle Deadlift": "轴杆硬拉",
  "Back Flyes - With Bands": "背部飞鸟-弹力带",
  "Backward Drag": "向后拖拽",
  "Backward Medicine Ball Throw": "向后药球投掷",
  "Balance Board": "平衡板",
  "Ball Leg Curl": "健身球腿弯举",
  "Band Assisted Pull-Up": "弹力带辅助引体向上",
  "Band Good Morning": "弹力带早安式",
  "Band Good Morning (Pull Through)": "弹力带早安式(拉通过)",
  "Band Hip Adductions": "弹力带髋内收",
  "Band Pull Apart": "弹力带拉开",
  "Band Skull Crusher": "弹力带碎颅者",
  "Barbell Ab Rollout": "杠铃健腹轮",
  "Barbell Ab Rollout - On Knees": "跪姿杠铃健腹轮",
  "Barbell Bench Press - Medium Grip": "杠铃卧推-中握",
  "Barbell Curl": "杠铃弯举",
  "Barbell Curls Lying Against An Incline": "杠铃弯举-仰卧对抗上斜",
  "Barbell Deadlift": "杠铃硬拉",
  "Barbell Full Squat": "杠铃完整深蹲",
  "Barbell Glute Bridge": "杠铃臀桥",
  "Barbell Guillotine Bench Press": "杠铃断头台卧推",
  "Barbell Hack Squat": "杠铃哈克深蹲",
  "Barbell Hip Thrust": "杠铃臀推",
  "Barbell Incline Bench Press - Medium Grip": "杠铃上斜卧推-中握",
  "Barbell Incline Shoulder Raise": "杠铃上斜肩举",
  "Barbell Lunge": "杠铃弓步",
  "Barbell Rear Delt Row": "杠铃后三角肌划船",
  "Barbell Rollout from Bench": "长凳杠铃滚轮",
  "Barbell Seated Calf Raise": "杠铃坐姿提踵",
  "Barbell Shoulder Press": "杠铃肩推举",
  "Barbell Shrug": "杠铃耸肩",
  "Barbell Shrug Behind The Back": "背后杠铃耸肩",
  "Barbell Side Bend": "杠铃侧弯曲",
  "Barbell Side Split Squat": "杠铃侧分腿蹲",
  "Barbell Squat": "杠铃深蹲",
  "Barbell Squat To A Bench": "凳上深蹲",
  "Barbell Step Ups": "杠铃上步",
  "Barbell Walking Lunge": "杠铃行走弓步",
  "Battling Ropes": "战绳",
  "Bear Crawl Sled Drags": "熊爬雪橇拖拽",
  "Behind Head Chest Stretch": "头后胸部拉伸",
  "Bench Dips": "长凳臂屈伸",
  "Bench Jump": "长凳跳",
  "Bench Press - Powerlifting": "卧推-力量举",
  "Bench Press - With Bands": "弹力带卧推",
  "Bench Press with Chains": "链条卧推",
  "Bench Sprint": "长凳冲刺",
  "Bent-Arm Barbell Pullover": "弯曲臂杠铃仰卧臂屈伸",
  "Bent-Arm Dumbbell Pullover": "弯曲臂哑铃仰卧臂屈伸",
  "Bent-Knee Hip Raise": "弯曲膝盖臀桥",
  "Bent Over Barbell Row": "俯身杠铃划船",
  "Bent Over Dumbbell Rear Delt Raise With Head On Bench": "俯身哑铃后三角肌举-头在凳上",
  "Bent Over Low-Pulley Side Lateral": "俯身低滑轮侧向",
  "Bent Over One-Arm Long Bar Row": "俯身单臂长杆划船",
  "Bent Over Two-Arm Long Bar Row": "俯身双臂长杆划船",
  "Bent Over Two-Dumbbell Row": "俯身双哑铃划船",
  "Bent Over Two-Dumbbell Row With Palms In": "俯身双哑铃划船-掌心向内",
  "Bent Press": "弯曲推举",
  "Bicycling": "骑自行车",
  "Bicycling, Stationary": "骑自行车-固定",
  "Board Press": "板推举",
  "Body-Up": "起身",
  "Body Tricep Press": "自重三头肌推举",
  "Bodyweight Flyes": "自重飞鸟",
  "Bodyweight Mid Row": "自重中部划船",
  "Bodyweight Squat": "自重深蹲",
  "Bodyweight Walking Lunge": "自重行走弓步",
  "Bosu Ball Cable Crunch With Side Bends": "波速球绳索卷腹-侧弯曲",
  "Bottoms-Up Clean From The Hang Position": "倒置翻举-从悬挂位置",
  "Bottoms Up": "倒置",
  "Box Jump (Multiple Response)": "跳箱(多重反应)",
  "Box Skip": "拳击跳步",
  "Box Squat": "拳击深蹲",
  "Box Squat with Bands": "弹力带拳击深蹲",
  "Box Squat with Chains": "链条拳击深蹲",
  "Brachialis-SMR": "肱肌筋膜放松",
  "Bradford/Rocky Presses": "布拉德福德/洛奇推举",
  "Butt-Ups": "臀桥卷腹",
  "Butt Lift (Bridge)": "臀部举起(桥式)",
  "Butterfly": "蝴蝶机飞鸟",
  "Cable Chest Press": "绳索胸推",
  "Cable Crossover": "龙门架夹胸",
  "Cable Crunch": "绳索卷腹",
  "Cable Deadlifts": "绳索硬拉",
  "Cable Hammer Curls - Rope Attachment": "绳索锤式弯举-爬绳附件",
  "Cable Hip Adduction": "绳索髋内收",
  "Cable Incline Pushdown": "绳索上斜下压",
  "Cable Incline Triceps Extension": "绳索上斜三头肌伸展",
  "Cable Internal Rotation": "绳索内部旋转",
  "Cable Iron Cross": "绳索铁十字",
  "Cable Judo Flip": "绳索柔道空翻",
  "Cable Lying Triceps Extension": "绳索仰卧三头肌伸展",
  "Cable One Arm Tricep Extension": "绳索单臂三头肌伸展",
  "Cable Preacher Curl": "绳索牧师凳弯举",
  "Cable Rear Delt Fly": "绳索后三角肌飞鸟",
  "Cable Reverse Crunch": "绳索反向卷腹",
  "Cable Rope Overhead Triceps Extension": "绳索爬绳过顶三头肌伸展",
  "Cable Rope Rear-Delt Rows": "绳索爬绳后三角肌划船",
  "Cable Russian Twists": "绳索俄式转体",
  "Cable Seated Crunch": "绳索坐姿卷腹",
  "Cable Seated Lateral Raise": "绳索坐姿侧平举",
  "Cable Shoulder Press": "绳索肩推举",
  "Cable Shrugs": "绳索耸肩",
  "Cable Wrist Curl": "绳索手腕弯举",
  "Calf-Machine Shoulder Shrug": "小腿器械肩耸肩",
  "Calf Press": "小腿推举",
  "Calf Press On The Leg Press Machine": "小腿推举-腿举器械",
  "Calf Raise On A Dumbbell": "哑铃提踵",
  "Calf Raises - With Bands": "弹力带提踵",
  "Calf Stretch Elbows Against Wall": "小腿拉伸-肘部靠墙",
  "Calf Stretch Hands Against Wall": "小腿拉伸-手靠墙",
  "Calves-SMR": "小腿筋膜放松",
  "Car Deadlift": "汽车硬拉",
  "Car Drivers": "汽车驾驶员训练",
  "Carioca Quick Step": "卡里奥卡快速踏步",
  "Cat Stretch": "猫式拉伸",
  "Catch and Overhead Throw": "接球过顶投掷",
  "Chain Handle Extension": "链条手柄伸展",
  "Chain Press": "链条推举",
  "Chair Leg Extended Stretch": "椅子腿部伸展拉伸",
  "Chair Lower Back Stretch": "椅子下背部拉伸",
  "Chair Squat": "椅子深蹲",
  "Chair Upper Body Stretch": "椅子上半身拉伸",
  "Chest And Front Of Shoulder Stretch": "胸和肩前部拉伸",
  "Chest Push from3 point stance": "三点站距胸推",
  "Chest Push (multiple response)": "胸推(多重反应)",
  "Chest Push (single response)": "胸推(单一反应)",
  "Chest Push with Run Release": "胸推-跑释放",
  "Chest Stretch on Stability Ball": "稳定球胸部拉伸",
  "Child's Pose": "婴儿式",
  "Chin-Up": "反握引体向上",
  "Chin To Chest Stretch": "下巴至胸部拉伸",
  "Circus Bell": "哑铃摆动",
  "Clean": "翻举",
  "Clean Deadlift": "翻举硬拉",
  "Clean Pull": "翻举拉",
  "Clean Shrug": "翻举耸肩",
  "Clean and Jerk": "翻举与挺举",
  "Clean and Press": "翻举与推举",
  "Clean from Blocks": "从架上翻举",
  "Clock Push-Up": "时钟俯卧撑",
  "Close-Grip Barbell Bench Press": "窄握杠铃卧推",
  "Close-Grip Dumbbell Press": "窄握哑铃推举",
  "Close-Grip EZ-Bar Curl with Band": "弹力带窄握曲杆弯举",
  "Close-Grip EZ-Bar Press": "窄握曲杆推举",
  "Close-Grip EZ Bar Curl": "窄握曲杆弯举",
  "Close-Grip Front Lat Pulldown": "窄握前背阔肌下拉",
  "Close-Grip Push-Up off of a Dumbbell": "窄握俯卧撑-离开哑铃",
  "Close-Grip Standing Barbell Curl": "窄握站姿杠铃弯举",
  "Cocoons": "茧式卷腹",
  "Conan's Wheel": "柯南之轮",
  "Concentration Curls": "集中弯举",
  "Cross-Body Crunch": "交叉身体卷腹",
  "Cross Body Hammer Curl": "交叉身体锤式弯举",
  "Cross Over - With Bands": "弹力带交叉",
  "Crossover Reverse Lunge": "交叉后退弓步",
  "Crucifix": "十字支撑",
  "Crunch - Hands Overhead": "卷腹-手过顶",
  "Crunch - Legs On Exercise Ball": "健身球卷腹",
  "Crunches": "卷腹",
  "Cuban Press": "古巴推举",
  "Dancer's Stretch": "舞者拉伸",
  "Dead Bug": "死虫式",
  "Deadlift with Bands": "弹力带硬拉",
  "Deadlift with Chains": "链条硬拉",
  "Decline Barbell Bench Press": "下斜杠铃卧推",
  "Decline Close-Grip Bench To Skull Crusher": "下斜窄握长凳碎颅者",
  "Decline Crunch": "下斜卷腹",
  "Decline Dumbbell Bench Press": "下斜哑铃卧推",
  "Decline Dumbbell Flyes": "下斜哑铃飞鸟",
  "Decline Dumbbell Triceps Extension": "下斜哑铃三头肌伸展",
  "Decline EZ Bar Triceps Extension": "下斜曲杆三头肌伸展",
  "Decline Oblique Crunch": "下斜腹斜肌卷腹",
  "Decline Push-Up": "下斜俯卧撑",
  "Decline Reverse Crunch": "下斜反向卷腹",
  "Decline Smith Press": "下斜史密斯机推举",
  "Deficit Deadlift": "赤字硬拉",
  "Depth Jump Leap": "深度跳跃远",
  "Dip Machine": "臂屈伸器械",
  "Dips - Chest Version": "胸肌版臂屈伸",
  "Dips - Triceps Version": "三头肌版臂屈伸",
  "Donkey Calf Raises": "驴式提踵",
  "Double Kettlebell Alternating Hang Clean": "双壶铃交替悬挂翻举",
  "Double Kettlebell Jerk": "双壶铃挺举",
  "Double Kettlebell Push Press": "双壶铃推推举",
  "Double Kettlebell Snatch": "双壶铃抓举",
  "Double Kettlebell Windmill": "双壶铃风车",
  "Double Leg Butt Kick": "双腿后踢",
  "Downward Facing Balance": "向下平衡",
  "Drag Curl": "拖拽弯举",
  "Drop Push": "下降推",
  "Dumbbell Alternate Bicep Curl": "哑铃交替二头弯举",
  "Dumbbell Bench Press": "哑铃卧推",
  "Dumbbell Bench Press with Neutral Grip": "对握哑铃卧推",
  "Dumbbell Bicep Curl": "哑铃二头弯举",
  "Dumbbell Clean": "哑铃翻举",
  "Dumbbell Floor Press": "哑铃地板推举",
  "Dumbbell Flyes": "哑铃飞鸟",
  "Dumbbell Incline Row": "哑铃上斜划船",
  "Dumbbell Incline Shoulder Raise": "哑铃上斜肩举",
  "Dumbbell Lunges": "哑铃弓步",
  "Dumbbell Lying One-Arm Rear Lateral Raise": "哑铃仰卧单臂后侧平举",
  "Dumbbell Lying Pronation": "哑铃仰卧旋前",
  "Dumbbell Lying Rear Lateral Raise": "哑铃仰卧后侧平举",
  "Dumbbell Lying Supination": "哑铃仰卧旋后",
  "Dumbbell One-Arm Shoulder Press": "哑铃单臂肩推举",
  "Dumbbell One-Arm Triceps Extension": "哑铃单臂三头肌伸展",
  "Dumbbell One-Arm Upright Row": "哑铃单臂直立划船",
  "Dumbbell Prone Incline Curl": "哑铃俯卧上斜弯举",
  "Dumbbell Raise": "哑铃举",
  "Dumbbell Rear Lunge": "哑铃后弓步",
  "Dumbbell Scaption": "哑铃肩胛平面举",
  "Dumbbell Seated Box Jump": "哑铃坐姿跳箱",
  "Dumbbell Seated One-Leg Calf Raise": "哑铃坐姿单腿提踵",
  "Dumbbell Shoulder Press": "哑铃肩推举",
  "Dumbbell Shrug": "哑铃耸肩",
  "Dumbbell Side Bend": "哑铃侧弯曲",
  "Dumbbell Squat": "哑铃深蹲",
  "Dumbbell Squat To A Bench": "哑铃深蹲上凳",
  "Dumbbell Step Ups": "哑铃上步",
  "Dumbbell Tricep Extension -Pronated Grip": "哑铃三头肌伸展-旋前握",
  "Dynamic Back Stretch": "动态背拉伸",
  "Dynamic Chest Stretch": "动态胸拉伸",
  "EZ-Bar Curl": "曲杆弯举",
  "EZ-Bar Skullcrusher": "曲杆碎颅者",
  "Elbow Circles": "肘部画圈",
  "Elbow to Knee": "肘部至膝盖",
  "Elbows Back": "肘部向后",
  "Elevated Back Lunge": "高垫背弓步",
  "Elevated Cable Rows": "高垫绳索划船",
  "Elliptical Trainer": "椭圆机",
  "Exercise Ball Crunch": "健身球卷腹",
  "Exercise Ball Pull-In": "健身球拉进",
  "Extended Range One-Arm Kettlebell Floor Press": "全范围单臂壶铃地板推举",
  "External Rotation": "外旋",
  "External Rotation with Band": "弹力带外旋",
  "External Rotation with Cable": "绳索外旋",
  "Face Pull": "面拉",
  "Farmer's Walk": "农夫行走",
  "Fast Skipping": "快速跳绳",
  "Finger Curls": "手指弯举",
  "Flat Bench Cable Flyes": "平板卧推绳索飞鸟",
  "Flat Bench Leg Pull-In": "平板卧推腿拉进",
  "Flat Bench Lying Leg Raise": "平板卧推仰卧举腿",
  "Flexor Incline Dumbbell Curls": "屈曲肌上斜哑铃弯举",
  "Floor Glute-Ham Raise": "地板臀腿举",
  "Floor Press": "地板推举",
  "Floor Press with Chains": "链条地板推举",
  "Flutter Kicks": "摆动踢",
  "Foot-SMR": "足底筋膜放松",
  "Forward Drag with Press": "向前拖拽推举",
  "Frankenstein Squat": "弗兰肯斯坦深蹲",
  "Freehand Jump Squat": "徒手跳深蹲",
  "Frog Hops": "青蛙跳",
  "Frog Sit-Ups": "青蛙仰卧起坐",
  "Front Barbell Squat": "前杠铃深蹲",
  "Front Barbell Squat To A Bench": "前杠铃深蹲上凳",
  "Front Box Jump": "前跳箱",
  "Front Cable Raise": "前绳索举",
  "Front Cone Hops (or hurdle hops)": "前锥桶跳(或跨栏跳)",
  "Front Dumbbell Raise": "前哑铃举",
  "Front Incline Dumbbell Raise": "前上斜哑铃举",
  "Front Leg Raises": "前举腿",
  "Front Plate Raise": "前杠铃片举",
  "Front Raise And Pullover": "前平举和仰卧臂屈伸",
  "Front Squat (Clean Grip)": "前蹲(翻举握)",
  "Front Squats With Two Kettlebells": "前蹲-双壶铃",
  "Front Two-Dumbbell Raise": "前双哑铃举",
  "Full Range-Of-Motion Lat Pulldown": "全范围背阔肌下拉",
  "Gironda Sternum Chins": "吉龙达胸骨引体",
  "Glute Ham Raise": "臀腿举",
  "Glute Kickback": "臀后踢",
  "Goblet Squat": "高脚杯深蹲",
  "Good Morning": "早安式",
  "Good Morning off Pins": "早安式离销",
  "Gorilla Chin/Crunch": "大猩猩引体/卷腹",
  "Groin and Back Stretch": "腹股沟和背拉伸",
  "Groiners": "腹股沟拉伸",
  "Hack Squat": "哈克深蹲",
  "Hammer Curls": "锤式弯举",
  "Hammer Grip Incline DB Bench Press": "锤握上斜哑铃卧推",
  "Hamstring-SMR": "腘绳肌筋膜放松",
  "Hamstring Stretch": "腘绳肌拉伸",
  "Handstand Push-Ups": "倒立撑",
  "Hang Clean": "悬挂翻举",
  "Hang Clean - Below Knees": "悬挂翻举-膝盖以下",
  "Hang Snatch": "悬挂抓举",
  "Hang Snatch - Below Knees": "悬挂抓举-膝盖以下",
  "Hanging Bar Good Morning": "悬挂杠早安式",
  "Hanging Leg Raise": "悬垂举腿",
  "Hanging Pike": "悬垂V字支撑",
  "Heaving Snatch Balance": "悬摆抓举平衡",
  "Heavy Bag Thrust": "重袋推举",
  "High Cable Curls": "高绳索弯举",
  "Hip Circles (prone)": "髋画圈(俯卧)",
  "Hip Extension with Bands": "弹力带髋伸展",
  "Hip Flexion with Band": "弹力带髋屈曲",
  "Hip Lift with Band": "弹力带髋举",
  "Hug A Ball": "抱球",
  "Hug Knees To Chest": "抱膝至胸",
  "Hurdle Hops": "跨栏跳",
  "Hyperextensions (Back Extensions)": "背伸(背部伸展)",
  "Hyperextensions With No Hyperextension Bench": "背伸-无背伸凳",
  "IT Band and Glute Stretch": "髂胫束弹力带和臀拉伸",
  "Iliotibial Tract-SMR": "髂胫束筋膜放松",
  "Inchworm": "尺蠖",
  "Incline Barbell Triceps Extension": "上斜杠铃三头肌伸展",
  "Incline Bench Pull": "上斜卧推拉",
  "Incline Cable Chest Press": "上斜绳索胸推",
  "Incline Cable Flye": "上斜绳索飞鸟",
  "Incline Dumbbell Bench With Palms Facing In": "上斜哑铃凳-掌心向内",
  "Incline Dumbbell Curl": "上斜哑铃弯举",
  "Incline Dumbbell Flyes": "上斜哑铃飞鸟",
  "Incline Dumbbell Flyes - With A Twist": "上斜哑铃飞鸟-转体",
  "Incline Dumbbell Press": "上斜哑铃推举",
  "Incline Hammer Curls": "上斜锤式弯举",
  "Incline Inner Biceps Curl": "上斜内侧二头弯举",
  "Incline Push-Up": "上斜俯卧撑",
  "Incline Push-Up Close-Grip": "上斜俯卧撑-窄握",
  "Incline Push-Up Depth Jump": "上斜俯卧撑深度跳",
  "Incline Push-Up Medium": "上斜俯卧撑-中等",
  "Incline Push-Up Reverse Grip": "上斜俯卧撑-反握",
  "Incline Push-Up Wide": "上斜俯卧撑-宽握",
  "Intermediate Groin Stretch": "中级腹股沟拉伸",
  "Intermediate Hip Flexor and Quad Stretch": "中级髋屈和四头肌拉伸",
  "Internal Rotation with Band": "弹力带内旋",
  "Inverted Row": "反向划船",
  "Inverted Row with Straps": "悬挂带反向划船",
  "Iron Cross": "铁十字",
  "Iron Crosses (stretch)": "铁十字拉伸",
  "Isometric Chest Squeezes": "等长胸挤压",
  "Isometric Neck Exercise - Front And Back": "等长颈部训练-前和后",
  "Isometric Neck Exercise - Sides": "等长颈部训练-两侧",
  "Isometric Wipers": "等长擦窗",
  "JM Press": "JM推举",
  "Jackknife Sit-Up": "杰克刀仰卧起坐",
  "Janda Sit-Up": "坚达仰卧起坐",
  "Jefferson Squats": "杰斐逊深蹲",
  "Jerk Balance": "挺举平衡",
  "Jerk Dip Squat": "挺举臂屈伸深蹲",
  "Jogging, Treadmill": "慢跑-跑步机",
  "Keg Load": "壶铃负重",
  "Kettlebell Arnold Press": "壶铃阿诺德推举",
  "Kettlebell Dead Clean": "壶铃悬挂翻举",
  "Kettlebell Figure 8": "壶铃8字形",
  "Kettlebell Hang Clean": "壶铃悬挂翻举",
  "Kettlebell One-Legged Deadlift": "壶铃单腿硬拉",
  "Kettlebell Pass Between The Legs": "壶铃穿过两腿",
  "Kettlebell Pirate Ships": "壶铃海盗船",
  "Kettlebell Pistol Squat": "壶铃手枪深蹲",
  "Kettlebell Seated Press": "壶铃坐姿推举",
  "Kettlebell Seesaw Press": "壶铃坐姿推举",
  "Kettlebell Sumo High Pull": "壶铃相扑高拉",
  "Kettlebell Thruster": "壶铃推举",
  "Kettlebell Turkish Get-Up (Lunge style)": "壶铃土耳其起身(弓步式)",
  "Kettlebell Turkish Get-Up (Squat style)": "壶铃土耳其起身(深蹲式)",
  "Kettlebell Windmill": "壶铃风车",
  "Kipping Muscle Up": "摆浪双力臂",
  "Knee Across The Body": "膝盖交叉身体",
  "Knee Circles": "膝盖画圈",
  "Knee/Hip Raise On Parallel Bars": "膝盖/臀桥在平行杆上",
  "Knee Tuck Jump": "膝盖屈膝跳",
  "Kneeling Arm Drill": "跪姿手臂训练",
  "Kneeling Cable Crunch With Alternating Oblique Twists": "跪姿绳索卷腹-交替腹斜肌转体",
  "Kneeling Cable Triceps Extension": "跪姿绳索三头肌伸展",
  "Kneeling Forearm Stretch": "跪姿前臂拉伸",
  "Kneeling High Pulley Row": "跪姿高滑轮划船",
  "Kneeling Hip Flexor": "跪姿髋屈曲",
  "Kneeling Jump Squat": "跪姿跳深蹲",
  "Kneeling Single-Arm High Pulley Row": "跪姿单臂高滑轮划船",
  "Kneeling Squat": "跪姿深蹲",
  "Landmine 180's": "地雷管180度",
  "Landmine Linear Jammer": "地雷管线性推击器",
  "Lateral Bound": "侧向跳跃",
  "Lateral Box Jump": "侧向跳箱",
  "Lateral Cone Hops": "侧向锥桶跳",
  "Lateral Raise - With Bands": "弹力带侧平举",
  "Latissimus Dorsi-SMR": "背阔肌筋膜放松",
  "Leg-Over Floor Press": "腿过地板推举",
  "Leg-Up Hamstring Stretch": "抬腿腘绳肌拉伸",
  "Leg Extensions": "腿屈伸",
  "Leg Lift": "举腿",
  "Leg Press": "腿举",
  "Leg Pull-In": "腿拉进",
  "Leverage Chest Press": "杠杆胸推",
  "Leverage Deadlift": "杠杆硬拉",
  "Leverage Decline Chest Press": "杠杆下斜胸推",
  "Leverage High Row": "杠杆高划船",
  "Leverage Incline Chest Press": "杠杆上斜胸推",
  "Leverage Iso Row": "杠杆等长划船",
  "Leverage Shoulder Press": "杠杆肩推举",
  "Leverage Shrug": "杠杆耸肩",
  "Linear 3-Part Start Technique": "线性三部分起始技术",
  "Linear Acceleration Wall Drill": "线性加速墙壁训练",
  "Linear Depth Jump": "线性深度跳",
  "Log Lift": "木杆举",
  "London Bridges": "伦敦桥式",
  "Looking At Ceiling": "仰望天花板",
  "Low Cable Crossover": "低龙门架交叉",
  "Low Cable Triceps Extension": "低绳索三头肌伸展",
  "Low Pulley Row To Neck": "低滑轮划船至颈部",
  "Lower Back-SMR": "下背部筋膜放松",
  "Lower Back Curl": "下背部弯举",
  "Lunge Pass Through": "弓步穿越",
  "Lunge Sprint": "弓步冲刺",
  "Lying Bent Leg Groin": "仰卧弯腿腹股沟",
  "Lying Cable Curl": "仰卧绳索弯举",
  "Lying Cambered Barbell Row": "仰卧弧形杠铃划船",
  "Lying Close-Grip Bar Curl On High Pulley": "仰卧窄握杠杆弯举-高滑轮",
  "Lying Close-Grip Barbell Triceps Extension Behind The Head": "仰卧窄握杠铃三头肌伸展-头后",
  "Lying Close-Grip Barbell Triceps Press To Chin": "仰卧窄握杠铃三头肌推举-至下巴",
  "Lying Crossover": "仰卧交叉",
  "Lying Dumbbell Tricep Extension": "仰卧哑铃三头肌伸展",
  "Lying Face Down Plate Neck Resistance": "仰卧杠铃片颈部抗阻",
  "Lying Face Up Plate Neck Resistance": "仰卧杠铃片颈部抗阻",
  "Lying Glute": "仰卧臀",
  "Lying Hamstring": "仰卧腘绳肌",
  "Lying High Bench Barbell Curl": "仰卧高凳杠铃弯举",
  "Lying Leg Curls": "仰卧腿弯举",
  "Lying Machine Squat": "仰卧器械深蹲",
  "Lying One-Arm Lateral Raise": "仰卧单臂侧平举",
  "Lying One-Arm Overhead Throw": "仰卧单臂过顶投掷",
  "Lying Prone Quadriceps": "仰卧俯卧股四头肌",
  "Lying Rear Delt Raise": "仰卧后三角肌举",
  "Lying Supine Dumbbell Curl": "仰卧仰卧哑铃弯举",
  "Lying T-Bar Row": "仰卧T杆划船",
  "Lying Triceps Press": "仰卧三头肌推举",
  "Machine Bench Press": "器械卧推",
  "Machine Bicep Curl": "器械二头弯举",
  "Machine Preacher Curls": "器械牧师凳弯举",
  "Machine Shoulder (Military) Press": "器械肩推举(军事式)",
  "Machine Triceps Extension": "器械三头肌伸展",
  "Medicine Ball Chest Pass": "药球胸前传",
  "Medicine Ball Full Twist": "药球完全转体",
  "Medicine Ball Scoop Throw": "药球投掷",
  "Middle Back Shrug": "中背部耸肩",
  "Middle Back Stretch": "中背部拉伸",
  "Mixed Grip Chin": "混合握引体",
  "Monster Walk": "怪兽行走",
  "Mountain Climbers": "登山者",
  "Moving Claw Series": "移动爪系列",
  "Muscle Snatch": "肌肉抓举",
  "Muscle Up": "双力臂",
  "Narrow Stance Hack Squats": "窄站距哈克深蹲",
  "Narrow Stance Leg Press": "窄站距腿举",
  "Narrow Stance Squats": "窄站距深蹲",
  "Natural Glute Ham Raise": "自然臀腿举",
  "Neck-SMR": "颈部筋膜放松",
  "Neck Press": "颈部推举",
  "Oblique Crunches": "腹斜肌卷腹",
  "Oblique Crunches - On The Floor": "腹斜肌卷腹-地板上",
  "Olympic Squat": "奥林匹克深蹲",
  "On-Your-Back Quad Stretch": "背部四头肌拉伸",
  "On Your Side Quad Stretch": "侧部四头肌拉伸",
  "One-Arm Dumbbell Row": "单臂哑铃划船",
  "One-Arm Flat Bench Dumbbell Flye": "单臂平板卧推哑铃飞鸟",
  "One-Arm High-Pulley Cable Side Bends": "单臂高滑轮绳索侧弯曲",
  "One-Arm Incline Lateral Raise": "单臂上斜侧平举",
  "One-Arm Kettlebell Clean": "单臂壶铃翻举",
  "One-Arm Kettlebell Clean and Jerk": "单臂壶铃翻举与挺举",
  "One-Arm Kettlebell Floor Press": "单臂壶铃地板推举",
  "One-Arm Kettlebell Jerk": "单臂壶铃挺举",
  "One-Arm Kettlebell Military Press To The Side": "单臂壶铃军事推举-至侧",
  "One-Arm Kettlebell Para Press": "单臂壶铃平行推举",
  "One-Arm Kettlebell Push Press": "单臂壶铃推推举",
  "One-Arm Kettlebell Row": "单臂壶铃划船",
  "One-Arm Kettlebell Snatch": "单臂壶铃抓举",
  "One-Arm Kettlebell Split Jerk": "单臂壶铃分腿挺举",
  "One-Arm Kettlebell Split Snatch": "单臂壶铃分腿抓举",
  "One-Arm Kettlebell Swings": "单臂壶铃摆动",
  "One-Arm Long Bar Row": "单臂长杆划船",
  "One-Arm Medicine Ball Slam": "单臂药球砸地",
  "One-Arm Open Palm Kettlebell Clean": "单臂开掌壶铃翻举",
  "One-Arm Overhead Kettlebell Squats": "单臂过顶壶铃深蹲",
  "One-Arm Side Deadlift": "单臂侧硬拉",
  "One-Arm Side Laterals": "单臂侧向",
  "One-Legged Cable Kickback": "单腿绳索后踢",
  "One Arm Against Wall": "单臂靠墙",
  "One Arm Chin-Up": "单臂引体向上",
  "One Arm Dumbbell Bench Press": "单臂哑铃卧推",
  "One Arm Dumbbell Preacher Curl": "单臂哑铃牧师凳弯举",
  "One Arm Floor Press": "单臂地板推举",
  "One Arm Lat Pulldown": "单臂背阔肌下拉",
  "One Arm Pronated Dumbbell Triceps Extension": "单臂旋前握哑铃三头肌伸展",
  "One Arm Supinated Dumbbell Triceps Extension": "单臂旋后握哑铃三头肌伸展",
  "One Half Locust": "单半蝗虫",
  "One Handed Hang": "单手悬挂",
  "One Knee To Chest": "单膝至胸",
  "One Leg Barbell Squat": "单腿杠铃深蹲",
  "Open Palm Kettlebell Clean": "开掌壶铃翻举",
  "Otis-Up": "臀屈伸",
  "Overhead Cable Curl": "过顶绳索弯举",
  "Overhead Lat": "过顶背阔肌",
  "Overhead Slam": "过顶砸",
  "Overhead Squat": "过顶深蹲",
  "Overhead Stretch": "过顶拉伸",
  "Overhead Triceps": "过顶三头肌",
  "Pallof Press": "高位推举",
  "Pallof Press With Rotation": "高位推举-旋转",
  "Palms-Down Dumbbell Wrist Curl Over A Bench": "掌心向下哑铃手腕弯举-在凳上",
  "Palms-Down Wrist Curl Over A Bench": "掌心向下手腕弯举-在凳上",
  "Palms-Up Barbell Wrist Curl Over A Bench": "掌心向上杠铃手腕弯举-在凳上",
  "Palms-Up Dumbbell Wrist Curl Over A Bench": "掌心向上哑铃手腕弯举-在凳上",
  "Parallel Bar Dip": "平行杆臂屈伸",
  "Pelvic Tilt Into Bridge": "骨盆倾斜成桥式",
  "Peroneals-SMR": "腓骨肌筋膜放松",
  "Peroneals Stretch": "腓骨肌拉伸",
  "Physioball Hip Bridge": "理疗球臀桥",
  "Pin Presses": "销推",
  "Piriformis-SMR": "梨状肌筋膜放松",
  "Plate Pinch": "杠铃片捏握",
  "Plate Twist": "杠铃片转体",
  "Platform Hamstring Slides": "平台腘绳肌滑行",
  "Plie Dumbbell Squat": "宽站哑铃深蹲",
  "Plyo Kettlebell Pushups": "增强式壶铃俯卧撑",
  "Plyo Push-up": "增强式俯卧撑",
  "Posterior Tibialis Stretch": "后胫骨拉伸",
  "Power Clean": "爆发力翻举",
  "Power Clean from Blocks": "从架上爆发力翻举",
  "Power Jerk": "爆发力挺举",
  "Power Partials": "爆发力部分",
  "Power Snatch": "爆发力抓举",
  "Power Snatch from Blocks": "从架上爆发力抓举",
  "Power Stairs": "力量阶梯",
  "Preacher Curl": "牧师凳弯举",
  "Preacher Hammer Dumbbell Curl": "牧师凳锤式哑铃弯举",
  "Press Sit-Up": "推举仰卧起坐",
  "Prone Manual Hamstring": "俯卧手动腘绳肌",
  "Prowler Sprint": "推雪橇冲刺",
  "Pull Through": "拉通过",
  "Pullups": "引体向上",
  "Push-Up Wide": "宽握俯卧撑",
  "Push-Ups - Close Triceps Position": "俯卧撑-三头肌收位",
  "Push-Ups With Feet Elevated": "脚垫高俯卧撑",
  "Push-Ups With Feet On An Exercise Ball": "健身球上俯卧撑",
  "Push Press": "推推举",
  "Push Press - Behind Neck": "推推举-颈后",
  "Push Up to Side Plank": "俯卧撑至侧平板支撑",
  "Pushups": "俯卧撑",
  "Pushups (Close and Wide Hand Positions)": "俯卧撑(窄握和宽握位)",
  "Pyramid": "金字塔",
  "Quad Stretch": "四头肌拉伸",
  "Quadriceps-SMR": "股四头肌筋膜放松",
  "Quick Leap": "快速跳跃",
  "Rack Delivery": "架上释放",
  "Rack Pull with Bands": "弹力带架上拉",
  "Rack Pulls": "架上拉",
  "Rear Leg Raises": "后举腿",
  "Recumbent Bike": "躺卧自行车",
  "Return Push from Stance": "转身推-从站姿",
  "Reverse Band Bench Press": "弹力带长凳卧推",
  "Reverse Band Box Squat": "弹力带拳击深蹲",
  "Reverse Band Deadlift": "弹力带硬拉",
  "Reverse Band Power Squat": "弹力带爆发力深蹲",
  "Reverse Band Sumo Deadlift": "弹力带相扑硬拉",
  "Reverse Barbell Curl": "反向杠铃弯举",
  "Reverse Barbell Preacher Curls": "反向杠铃牧师凳弯举",
  "Reverse Cable Curl": "反向绳索弯举",
  "Reverse Crunch": "反向卷腹",
  "Reverse Flyes": "反向飞鸟",
  "Reverse Flyes With External Rotation": "反向飞鸟-外旋",
  "Reverse Grip Bent-Over Rows": "反握俯身划船",
  "Reverse Grip Triceps Pushdown": "反握三头肌下压",
  "Reverse Hyperextension": "反向背伸",
  "Reverse Machine Flyes": "反向器械飞鸟",
  "Reverse Plate Curls": "杠铃片弯举",
  "Reverse Triceps Bench Press": "反向三头肌卧推",
  "Rhomboids-SMR": "菱形肌筋膜放松",
  "Rickshaw Carry": "人力车搬运",
  "Rickshaw Deadlift": "人力车硬拉",
  "Ring Dips": "吊环臂屈伸",
  "Rocket Jump": "火箭跳",
  "Rocking Standing Calf Raise": "摇动站姿提踵",
  "Rocky Pull-Ups/Pulldowns": "洛奇引体向上/下拉",
  "Romanian Deadlift": "罗马尼亚硬拉",
  "Romanian Deadlift from Deficit": "赤字罗马尼亚硬拉",
  "Rope Climb": "爬绳",
  "Rope Crunch": "爬绳卷腹",
  "Rope Jumping": "爬绳跳跃",
  "Rope Straight-Arm Pulldown": "爬绳直臂下拉",
  "Round The World Shoulder Stretch": "环绕世界肩拉伸",
  "Rowing, Stationary": "划船-固定",
  "Runner's Stretch": "跑者拉伸",
  "Running, Treadmill": "跑步-跑步机",
  "Russian Twist": "俄式转体",
  "Sandbag Load": "沙袋负重",
  "Scapular Pull-Up": "肩胛引体向上",
  "Scissor Kick": "剪刀踢",
  "Scissors Jump": "剪刀跳",
  "Seated Band Hamstring Curl": "坐姿弹力带腘绳肌弯举",
  "Seated Barbell Military Press": "坐姿杠铃军事推举",
  "Seated Barbell Twist": "坐姿杠铃转体",
  "Seated Bent-Over One-Arm Dumbbell Triceps Extension": "坐姿俯身单臂哑铃三头肌伸展",
  "Seated Bent-Over Rear Delt Raise": "坐姿俯身后三角肌举",
  "Seated Bent-Over Two-Arm Dumbbell Triceps Extension": "坐姿俯身双臂哑铃三头肌伸展",
  "Seated Biceps": "坐姿二头",
  "Seated Cable Rows": "坐姿绳索划船",
  "Seated Cable Shoulder Press": "坐姿绳索肩推举",
  "Seated Calf Raise": "坐姿提踵",
  "Seated Calf Stretch": "坐姿小腿拉伸",
  "Seated Close-Grip Concentration Barbell Curl": "坐姿窄握集中杠铃弯举",
  "Seated Dumbbell Curl": "坐姿哑铃弯举",
  "Seated Dumbbell Inner Biceps Curl": "坐姿哑铃内侧二头弯举",
  "Seated Dumbbell Palms-Down Wrist Curl": "坐姿哑铃掌心向下手腕弯举",
  "Seated Dumbbell Palms-Up Wrist Curl": "坐姿哑铃掌心向上手腕弯举",
  "Seated Dumbbell Press": "坐姿哑铃推举",
  "Seated Dumbbell Reverse Curl": "坐姿哑铃反向弯举",
  "Seated Dumbbell Shoulder Press": "坐姿哑铃肩推举",
  "Seated Flat Bench Leg Pull-In": "坐姿平板卧推腿拉进",
  "Seated Floor Hamstring Stretch": "坐姿地板腘绳肌拉伸",
  "Seated Front Deltoid": "坐姿前三角肌",
  "Seated Glute": "坐姿臀",
  "Seated Good Mornings": "坐姿早安式",
  "Seated Hamstring": "坐姿腘绳肌",
  "Seated Hamstring and Calf Stretch": "坐姿腘绳肌和小腿拉伸",
  "Seated Head Harness Neck Resistance": "坐姿头颈部抗阻站距",
  "Seated Leg Curl": "坐姿腿弯举",
  "Seated Leg Tucks": "坐姿腿收屈",
  "Seated One-Arm Dumbbell Palms-Down Wrist Curl": "坐姿单臂哑铃掌心向下手腕弯举",
  "Seated One-Arm Dumbbell Palms-Up Wrist Curl": "坐姿单臂哑铃掌心向上手腕弯举",
  "Seated One-Arm Cable Pulley Rows": "坐姿单臂绳索滑轮划船",
  "Seated Overhead Stretch": "坐姿过顶拉伸",
  "Seated Palm-Up Barbell Wrist Curl": "坐姿掌心向上杠铃手腕弯举",
  "Seated Palms-Down Barbell Wrist Curl": "坐姿掌心向下杠铃手腕弯举",
  "Seated Side Lateral Raise": "坐姿侧平举",
  "Seated Triceps Press": "坐姿三头肌推举",
  "Seated Two-Arm Palms-Up Low-Pulley Wrist Curl": "坐姿双臂掌心向上低滑轮手腕弯举",
  "See-Saw Press (Alternating Side Press)": "锯式推举(交替侧推)",
  "Shotgun Row": "霰弹枪划船",
  "Shoulder Circles": "肩画圈",
  "Shoulder Press - With Bands": "弹力带肩推举",
  "Shoulder Raise": "肩举",
  "Shoulder Stretch": "肩拉伸",
  "Side-Lying Floor Stretch": "侧仰卧地板拉伸",
  "Side Bridge": "侧桥式",
  "Side Hop-Sprint": "侧跳跃冲刺",
  "Side Jackknife": "侧杰克刀",
  "Side Lateral Raise": "侧平举",
  "Side Laterals to Front Raise": "侧向前平举",
  "Side Leg Raises": "侧举腿",
  "Side Lying Groin Stretch": "侧仰卧腹股沟拉伸",
  "Side Neck Stretch": "侧颈部拉伸",
  "Side Standing Long Jump": "侧站姿跳远",
  "Side to Side Chins": "侧对侧引体",
  "Side Wrist Pull": "侧手腕拉",
  "Side to Side Box Shuffle": "侧对侧拳击滑步",
  "Single-Arm Cable Crossover": "单臂龙门架交叉",
  "Single-Arm Linear Jammer": "单臂线性推击器",
  "Single-Arm Push-Up": "单臂俯卧撑",
  "Single-Cone Sprint Drill": "单锥桶冲刺训练",
  "Single-Leg High Box Squat": "单腿高跳箱深蹲",
  "Single-Leg Hop Progression": "单腿跳进展",
  "Single-Leg Lateral Hop": "单腿侧跳",
  "Single-Leg Leg Extension": "单腿腿屈伸",
  "Single-Leg Stride Jump": "单腿跨跳",
  "Single Dumbbell Raise": "单哑铃举",
  "Single Leg Butt Kick": "单腿后踢",
  "Single Leg Glute Bridge": "单腿臀桥",
  "Single Leg Push-off": "单腿推离",
  "Sit-Up": "仰卧起坐",
  "Sit Squats": "椅式深蹲",
  "Skating": "滑冰",
  "Sled Drag - Harness": "雪橇拖拽-吊带",
  "Sled Overhead Backward Walk": "雪橇过顶向后行走",
  "Sled Overhead Triceps Extension": "雪橇过顶三头肌伸展",
  "Sled Push": "推雪橇",
  "Sled Reverse Flye": "雪橇反向飞鸟",
  "Sled Row": "雪橇划船",
  "Sledgehammer Swings": "大锤摆动",
  "Smith Incline Shoulder Raise": "史密斯机上斜肩举",
  "Smith Machine Behind The Back Shrug": "史密斯器械背后耸肩",
  "Smith Machine Bench Press": "史密斯器械卧推",
  "Smith Machine Bent Over Row": "史密斯器械俯身划船",
  "Smith Machine Calf Raise": "史密斯器械提踵",
  "Smith Machine Close-Grip Bench Press": "史密斯器械窄握卧推",
  "Smith Machine Decline Press": "史密斯器械下斜推",
  "Smith Machine Hip Raise": "史密斯器械臀桥",
  "Smith Machine Incline Bench Press": "史密斯器械上斜卧推",
  "Smith Machine Leg Press": "史密斯器械腿举",
  "Smith Machine One-Arm Upright Row": "史密斯器械单臂直立划船",
  "Smith Machine Overhead Shoulder Press": "史密斯器械过顶肩推举",
  "Smith Machine Pistol Squat": "史密斯器械手枪深蹲",
  "Smith Machine Reverse Calf Raises": "史密斯器械反向提踵",
  "Smith Machine Squat": "史密斯器械深蹲",
  "Smith Machine Stiff-Legged Deadlift": "史密斯器械直腿硬拉",
  "Smith Machine Upright Row": "史密斯器械直立划船",
  "Smith Machine Single-Leg Split Squat": "史密斯器械单腿分腿蹲",
  "Snatch": "抓举",
  "Snatch Balance": "抓举平衡",
  "Snatch Deadlift": "抓举硬拉",
  "Snatch Pull": "抓举拉",
  "Snatch Shrug": "抓举耸肩",
  "Snatch from Blocks": "从架上抓举",
  "Speed Band Overhead Triceps": "速度弹力带过顶三头肌",
  "Speed Box Squat": "速度拳击深蹲",
  "Speed Squats": "速度深蹲",
  "Spell Caster": "旋转投掷器",
  "Spider Crawl": "蜘蛛爬",
  "Spider Curl": "蜘蛛弯举",
  "Spinal Stretch": "脊柱拉伸",
  "Split Clean": "分腿翻举",
  "Split Jerk": "分腿挺举",
  "Split Jump": "分腿跳",
  "Split Snatch": "分腿抓举",
  "Split Squat": "分腿蹲",
  "Split Squat with Dumbbells": "哑铃分腿蹲",
  "Split Squats": "分腿蹲",
  "Squat Jerk": "深蹲挺举",
  "Squat with Bands": "弹力带深蹲",
  "Squat with Chains": "链条深蹲",
  "Squat with Plate Movers": "杠铃片深蹲",
  "Squats - With Bands": "弹力带深蹲",
  "Stairmaster": "踏步机",
  "Standing Alternating Dumbbell Press": "站姿交替哑铃推举",
  "Standing Barbell Calf Raise": "站姿杠铃提踵",
  "Standing Barbell Press Behind Neck": "站姿杠铃推举-颈后",
  "Standing Bent-Over One-Arm Dumbbell Triceps Extension": "站姿俯身单臂哑铃三头肌伸展",
  "Standing Bent-Over Two-Arm Dumbbell Triceps Extension": "站姿俯身双臂哑铃三头肌伸展",
  "Standing Biceps Cable Curl": "站姿二头绳索弯举",
  "Standing Biceps Stretch": "站姿二头拉伸",
  "Standing Bradford Press": "站姿布拉德福德推举",
  "Standing Cable Chest Press": "站姿绳索胸推",
  "Standing Cable Lift": "站姿绳索举起",
  "Standing Cable Wood Chop": "站姿绳索砍举",
  "Standing Calf Raises": "站姿提踵",
  "Standing Concentration Curl": "站姿集中弯举",
  "Standing Dumbbell Calf Raise": "站姿哑铃提踵",
  "Standing Dumbbell Press": "站姿哑铃推举",
  "Standing Dumbbell Reverse Curl": "站姿哑铃反向弯举",
  "Standing Dumbbell Straight-Arm Front Delt Raise Above Head": "站姿哑铃直臂前三角肌举-过头顶",
  "Standing Dumbbell Triceps Extension": "站姿哑铃三头肌伸展",
  "Standing Dumbbell Upright Row": "站姿哑铃直立划船",
  "Standing Elevated Quad Stretch": "站姿高位四头肌拉伸",
  "Standing Gastrocnemius Calf Stretch": "站姿腓肠肌小腿拉伸",
  "Standing Hamstring and Calf Stretch": "站姿腘绳肌和小腿拉伸",
  "Standing Hip Circles": "站姿髋画圈",
  "Standing Hip Flexors": "站姿髋屈曲",
  "Standing Inner-Biceps Curl": "站姿内侧二头弯举",
  "Standing Lateral Stretch": "站姿侧向拉伸",
  "Standing Leg Curl": "站姿腿弯举",
  "Standing Long Jump": "站姿跳远",
  "Standing Low-Pulley Deltoid Raise": "站姿低滑轮三角肌举",
  "Standing Low-Pulley One-Arm Triceps Extension": "站姿低滑轮单臂三头肌伸展",
  "Standing Military Press": "站姿军事推举",
  "Standing Olympic Plate Hand Squeeze": "站姿奥林匹克杠铃片手挤压",
  "Standing One-Arm Cable Curl": "站姿单臂绳索弯举",
  "Standing One-Arm Dumbbell Curl Over Incline Bench": "站姿单臂哑铃弯举-上斜卧推",
  "Standing One-Arm Dumbbell Triceps Extension": "站姿单臂哑铃三头肌伸展",
  "Standing One-Arm Kettlebell Clean and Jerk": "站姿单臂壶铃翻举与挺举",
  "Standing One-Arm Kettlebell Floor Press": "站姿单臂壶铃地板推举",
  "Standing One-Arm Kettlebell Jerk": "站姿单臂壶铃挺举",
  "Standing One-Arm Kettlebell Military Press To The Side": "站姿单臂壶铃军事推举-至侧",
  "Standing One-Arm Kettlebell Para Press": "站姿单臂壶铃平行推举",
  "Standing One-Arm Kettlebell Push Press": "站姿单臂壶铃推推举",
  "Standing One-Arm Kettlebell Row": "站姿单臂壶铃划船",
  "Standing One-Arm Kettlebell Snatch": "站姿单臂壶铃抓举",
  "Standing One-Arm Kettlebell Split Jerk": "站姿单臂壶铃分腿挺举",
  "Standing One-Arm Kettlebell Split Snatch": "站姿单臂壶铃分腿抓举",
  "Standing One-Arm Kettlebell Swings": "站姿单臂壶铃摆动",
  "Standing One-Arm Side Deadlift": "站姿单臂侧硬拉",
  "Standing One-Arm Side Laterals": "站姿单臂侧向",
  "Standing One-Legged Cable Kickback": "站姿单腿绳索后踢",
  "Standing One Leg Glute Bridge": "站姿单腿臀桥",
  "Standing One Leg Push-off": "站姿单腿推离",
  "Standing Palms-In Dumbbell Press": "站姿掌心向内哑铃推举",
  "Standing Palms-In Dumbbell Wrist Curl": "站姿掌心向内哑铃手腕弯举",
  "Standing Palms-Up Barbell Wrist Curl": "站姿掌心向上杠铃手腕弯举",
  "Standing Palms-Up Dumbbell Wrist Curl Over A Bench": "站姿掌心向上哑铃手腕弯举-在凳上",
  "Standing Palms-Up Dumbbell Wrist Curl Over A Bench": "站姿掌心向上哑铃手腕弯举-在凳上",
  "Standing Pelvic Tilt": "站姿骨盆倾斜",
  "Standing Rope Crunch": "站姿爬绳卷腹",
  "Standing Soleus And Achilles Stretch": "站姿小腿跟和跟腱拉伸",
  "Standing Toe Touches": "站姿脚趾触碰",
  "Standing Towel Triceps Extension": "站姿毛巾三头肌伸展",
  "Standing Two-Arm Overhead Throw": "站姿双臂过顶投掷",
  "Star Jump": "星跳",
  "Step-up with Knee Raise": "上步-屈膝举腿",
  "Step Mill": "踏步器",
  "Stiff-Legged Barbell Deadlift": "直腿杠铃硬拉",
  "Stiff-Legged Dumbbell Deadlift": "直腿哑铃硬拉",
  "Stiff Leg Barbell Good Morning": "直腿杠铃早安式",
  "Stomach Vacuum": "腹式呼吸",
  "Straight-Arm Dumbbell Pullover": "直臂哑铃仰卧臂屈伸",
  "Straight-Arm Pulldown": "直臂下拉",
  "Straight Bar Bench Mid Rows": "直杆长凳中段划船",
  "Straight Bar Bench Press": "直杆长凳卧推",
  "Straight Raises on Incline Bench": "上斜卧推直举",
  "Stride Jump Crossover": "跨跳交叉",
  "Sumo Deadlift": "相扑硬拉",
  "Sumo Deadlift with Bands": "弹力带相扑硬拉",
  "Sumo Deadlift with Chains": "链条相扑硬拉",
  "Superman": "超人",
  "Supine Chest Throw": "仰卧胸投",
  "Supine One-Arm Overhead Throw": "仰卧单臂过顶投掷",
  "Supine Two-Arm Overhead Throw": "仰卧双臂过顶投掷",
  "Suspended Fallout": "悬挂落下",
  "Suspended Push-Up": "悬挂俯卧撑",
  "Suspended Reverse Crunch": "悬挂反向卷腹",
  "Suspended Row": "悬挂划船",
  "Suspended Split Squat": "悬挂分腿蹲",
  "Svend Press": "斯文德推举",
  "T-Bar Row with Handle": "T杆划船-带手柄",
  "Tate Press": "斜板推举",
  "The Straddle": "分腿蹲",
  "Thigh Abductor": "大腿外展肌",
  "Thigh Adductor": "大腿内收肌",
  "Tire Flip": "轮胎翻转",
  "Toe Touchers": "脚趾触碰",
  "Torso Rotation": "躯干旋转",
  "Trail Running/Walking": "越野跑/走",
  "Trap Bar Deadlift": "斜方肌杠硬拉",
  "Tricep Dumbbell Kickback": "三头肌哑铃后踢",
  "Tricep Side Stretch": "三头肌侧拉伸",
  "Triceps Overhead Extension with Rope": "三头肌过顶伸展-爬绳",
  "Triceps Pushdown": "三头肌下压",
  "Triceps Pushdown - Rope Attachment": "三头肌下压-爬绳附件",
  "Triceps Pushdown - V-Bar Attachment": "三头肌下压-V杆附件",
  "Triceps Stretch": "三头肌拉伸",
  "Tuck Crunch": "屈膝卷腹",
  "Two-Arm Dumbbell Preacher Curl": "双臂哑铃牧师凳弯举",
  "Two-Arm Kettlebell Clean": "双臂壶铃翻举",
  "Two-Arm Kettlebell Jerk": "双臂壶铃挺举",
  "Two-Arm Kettlebell Military Press": "双臂壶铃军事推举",
  "Two-Arm Kettlebell Row": "双臂壶铃划船",
  "Underhand Cable Pulldowns": "反握绳索下拉",
  "Upper Back-Leg Grab": "上背部抓腿",
  "Upper Back Stretch": "上背部拉伸",
  "Upright Barbell Row": "直立杠铃划船",
  "Upright Cable Row": "直立绳索划船",
  "Upright Row - With Bands": "弹力带直立划船",
  "Upward Stretch": "向上拉伸",
  "V-Bar Pulldown": "V杆下拉",
  "V-Bar Pullup": "V杆引体向上",
  "Vertical Swing": "垂直摆动",
  "Walking, Treadmill": "行走-跑步机",
  "Weighted Ball Hyperextension": "负重球背伸",
  "Weighted Ball Side Bend": "负重球侧弯曲",
  "Weighted Bench Dip": "负重长凳臂屈伸",
  "Weighted Crunches": "负重卷腹",
  "Weighted Jump Squat": "负重跳深蹲",
  "Weighted Pull Ups": "负重引体向上",
  "Weighted Sissy Squat": "负重西西深蹲",
  "Weighted Sit-Ups - With Bands": "负重仰卧起坐-弹力带",
  "Weighted Squat": "负重深蹲",
  "Wide-Grip Barbell Bench Press": "宽握杠铃卧推",
  "Wide-Grip Decline Barbell Bench Press": "宽握下斜杠铃卧推",
  "Wide-Grip Decline Barbell Pullover": "宽握下斜杠铃仰卧臂屈伸",
  "Wide-Grip Lat Pulldown": "宽握背阔肌下拉",
  "Wide-Grip Pulldown Behind The Neck": "宽握下拉-颈后",
  "Wide-Grip Rear Pull-Up": "宽握后引体向上",
  "Wide-Grip Standing Barbell Curl": "宽握站姿杠铃弯举",
  "Wide Stance Barbell Squat": "宽站距杠铃深蹲",
  "Wide Stance Stiff Legs": "宽站距直腿",
  "Wind Sprints": "风冲刺",
  "Windmills": "风车",
  "World's Greatest Stretch": "世界拉伸",
  "Wrist Circles": "手腕画圈",
  "Wrist Roller": "手腕滚轮",
  "Wrist Rotations with Straight Bar": "直杆手腕旋转",
  "Yoke Walk": "拖举行走",
  "Zercher Squats": "深蹲",
  "Zottman Curl": "佐特曼弯举",
  "Zottman Preacher Curl": "佐特曼牧师凳弯举"
}